setup.py
allinpractice/__init__.py
allinpractice/app.py
allinpractice.egg-info/PKG-INFO
allinpractice.egg-info/SOURCES.txt
allinpractice.egg-info/dependency_links.txt
allinpractice.egg-info/requires.txt
allinpractice.egg-info/top_level.txt