Metadata-Version: 1.0
Name: allinpractice
Version: 0.0.2
Summary: All-Inspiration Practice Back-end
Home-page: https://github.com/frugs/allin-practice-backend
Author: Hugo Wainwright
Author-email: wainwrighthugo@gmail.com
License: UNKNOWN
Keywords: sc2,all-inspiration
Platform: UNKNOWN
